{
    "title": "Apple Store",
    "group1": [
        {
            "id": "G1-1",
            "name": "Huancayo",
            "group2": [
                {
                    "id": "G2-1",
                    "name": "Henry Ramirez",
                    "group3": [
                        {
                            "id": "G3-1",
                            "name": "iPhone 14"
                        },
                        {
                            "id": "G3-2",
                            "name": "AirPods Pro"
                        }
                    ]
                },
                {
                    "id": "G2-2",
                    "name": "Jesus Llacta",
                    "group3": [
                        {
                            "id": "G3-1",
                            "name": "MacBook Pro"
                        }
                    ]
                }
            ]
        },
        {
            "id": "G1-2",
            "name": "Lima",
            "group2": [
                {
                    "id": "G2-1",
                    "name": "Lionel Messi",
                    "group3": [
                        {
                            "id": "G3-1",
                            "name": "Home Pod Mini"
                        }
                    ]
                },
                {
                    "id": "G2-2",
                    "name": "Cristiano ronaldo",
                    "group3": [
                        {
                            "id": "G3-1",
                            "name": "iPhone 12 Mini"
                        },
                        {
                            "id": "G3-2",
                            "name": "Apple Watch"
                        },
                        {
                            "id": "G3-3",
                            "name": "Apple Tv"
                        }
                    ]
                }
            ]
        }
    ]
}